LICENSE
README.md
setup.cfg
setup.py
pymorphapi/__init__.py
pymorphapi.egg-info/PKG-INFO
pymorphapi.egg-info/SOURCES.txt
pymorphapi.egg-info/dependency_links.txt
pymorphapi.egg-info/requires.txt
pymorphapi.egg-info/top_level.txt