Metadata-Version: 2.1
Name: pymorphapi
Version: 1.9.5
Summary: Common Morpheus API calls for HOL Events
Home-page: https://github.com/joetitra/pymorphapi
Author: Joe Titra
Author-email: jtitra@gmail.com
License: MIT License
Platform: UNKNOWN
Classifier: Programming Language :: Python :: 3
Classifier: License :: OSI Approved :: MIT License
Classifier: Operating System :: OS Independent
